Workbook

Sheet Listas
A1: 0. Custos Diretos | B1: Clínico | C1: Crédito | D1: Sim
A2: 1. Administrativa | B2: Ortodontia | C2: Débito | D2: Não
A3: 2.Financeira | B3: Prótese | C3: PIX
A4: 3.Ocupação | B4: Implante | C4: Financeira
A5: 4.Despesas com Marketing | B5: Estética | C5: Dinheiro
A6: 5.Despesa com Utilidades | B6: Avaliação | C6: Boleto
A7: 6.Despesa com Pessoal | C7: Convênio
A8: 7.Despesas Comerciais
A9: 9. Administração Pinheiro
A10: 10.Tributos
A11: Deduções da Receita Bruta
A12: Despesas Empreendedor

Sheet Calendário
C1: CALENDÁRIO · SETEMBRO 2026
C2: Marque Não nos dias que a clínica não abre — feriado, folga, o que for. A meta se redistribui sozinha entre os dias que sobram.
C4: Meta do mês | D4: 78000 | E4: =COUNTIF(D7:D36,"Sim") -> 26 | F4: dias que a clínica abre
C6: Data | D6: Trabalha? | E6: Meta do dia
C7: 46266 | D7: Sim | E7: =IF($D7="Sim",IFERROR($D$4/$E$4,0),0) -> 3000
C8: 46267 | D8: Sim | E8: =IF($D8="Sim",IFERROR($D$4/$E$4,0),0) -> 3000
C9: 46268 | D9: Sim | E9: =IF($D9="Sim",IFERROR($D$4/$E$4,0),0) -> 3000
C10: 46269 | D10: Sim | E10: =IF($D10="Sim",IFERROR($D$4/$E$4,0),0) -> 3000
C11: 46270 | D11: Sim | E11: =IF($D11="Sim",IFERROR($D$4/$E$4,0),0) -> 3000
C12: 46271 | D12: Não | E12: =IF($D12="Sim",IFERROR($D$4/$E$4,0),0) -> 0
C13: 46272 | D13: Sim | E13: =IF($D13="Sim",IFERROR($D$4/$E$4,0),0) -> 3000
C14: 46273 | D14: Sim | E14: =IF($D14="Sim",IFERROR($D$4/$E$4,0),0) -> 3000
C15: 46274 | D15: Sim | E15: =IF($D15="Sim",IFERROR($D$4/$E$4,0),0) -> 3000
C16: 46275 | D16: Sim | E16: =IF($D16="Sim",IFERROR($D$4/$E$4,0),0) -> 3000
C17: 46276 | D17: Sim | E17: =IF($D17="Sim",IFERROR($D$4/$E$4,0),0) -> 3000
C18: 46277 | D18: Sim | E18: =IF($D18="Sim",IFERROR($D$4/$E$4,0),0) -> 3000
... C36: 46295 | D36: Sim | E36: =IF($D36="Sim",IFERROR($D$4/$E$4,0),0) -> 3000

Sheet Movimento
C1: SORRISO MAIOR · SETEMBRO 2026
C2: Cada venda, uma linha, uma vez só. Procedimento e forma de pagamento na mesma linha — todo o resto da planilha lê daqui.
C4: Vendido até agora | D4: =SUM($F$8:$F$407) -> 0 | E4: Meta do mês | F4: =Calendário!$D$4 -> 78000 | G4: Atingimento | H4: =IFERROR($D$4/$F$4,0) -> 0 | I4: Tendência | J4: =IFERROR($D$4/MAX(1,COUNTIFS(Calendário!$D$7:$D$37,"Sim",Calendário!$C$7:$C$37,"<="&TODAY()))*Calendário!$E$4,0) -> 0
C7: Data | D7: Procedimento | E7: Forma de recebimento | F7: Valor | G7: Paciente / Obs.

Sheet Despesas
C1: DESPESAS · SETEMBRO 2026
C2: Cada saída, uma linha. Vira custo no Resumo e no DRE.
C5: Total no mês | D5: =SUM($F$8:$F$207) -> 0
C7: Data | D7: Categoria | E7: Fornecedor / Descrição | F7: Valor | G7: Status

Sheet Dia a Dia
C1: DIA A DIA · SETEMBRO 2026
C2: Nada se digita aqui. Cada linha lê do Movimento e do Calendário.
C6: Data | D6: Trabalha | E6: Meta do dia | F6: Vendido | G6: % da meta | H6: Bateu? | I6: Acumulado | J6: Meta acum. | K6: Dif. acum.
C7: =Calendário!C7 -> 46266 | D7: =Calendário!D7 -> Sim | E7: =Calendário!E7 -> 3000 | F7: =SUMPRODUCT((Movimento!$C$8:$C$407<>"")*(TEXT(Movimento!$C$8:$C$407,"yyyy-mm-dd")=TEXT($C7,"yyyy-mm-dd"))*Movimento!$F$8:$F$407) -> 0 | G7: =IF($E7=0,"",IFERROR($F7/$E7,0)) -> 0 | H7: =IF(AND($E7>0,$F7>=$E7),1,0) -> 0 | I7: =$F7 -> 0 | J7: =$E7 -> 3000 | K7: =I7-J7 -> -3000
C8: =Calendário!C8 -> 46267 | D8: =Calendário!D8 -> Sim | E8: =Calendário!E8 -> 3000 | F8: =SUMPRODUCT((Movimento!$C$8:$C$407<>"")*(TEXT(Movimento!$C$8:$C$407,"yyyy-mm-dd")=TEXT($C8,"yyyy-mm-dd"))*Movimento!$F$8:$F$407) -> 0 | G8: =IF($E8=0,"",IFERROR($F8/$E8,0)) -> 0 | H8: =IF(AND($E8>0,$F8>=$E8),1,0) -> 0 | I8: =I7+$F8 -> 0 | J8: =J7+$E8 -> 6000 | K8: =I8-J8 -> -6000
C9: =Calendário!C9 -> 46268 | D9: =Calendário!D9 -> Sim | E9: =Calendário!E9 -> 3000 | F9: =SUMPRODUCT((Movimento!$C$8:$C$407<>"")*(TEXT(Movimento!$C$8:$C$407,"yyyy-mm-dd")=TEXT($C9,"yyyy-mm-dd"))*Movimento!$F$8:$F$407) -> 0 | G9: =IF($E9=0,"",IFERROR($F9/$E9,0)) -> 0 | H9: =IF(AND($E9>0,$F9>=$E9),1,0) -> 0 | I9: =I8+$F9 -> 0 | J9: =J8+$E9 -> 9000 | K9: =I9-J9 -> -9000
C10: =Calendário!C10 -> 46269 | D10: =Calendário!D10 -> Sim | E10: =Calendário!E10 -> 3000 | F10: =SUMPRODUCT((Movimento!$C$8:$C$407<>"")*(TEXT(Movimento!$C$8:$C$407,"yyyy-mm-dd")=TEXT($C10,"yyyy-mm-dd"))*Movimento!$F$8:$F$407) -> 0 | G10: =IF($E10=0,"",IFERROR($F10/$E10,0)) -> 0 | H10: =IF(AND($E10>0,$F10>=$E10),1,0) -> 0 | I10: =I9+$F10 -> 0 | J10: =J9+$E10 -> 12000 | K10: =I10-J10 -> -12000
C11: =Calendário!C11 -> 46270 | D11: =Calendário!D11 -> Sim | E11: =Calendário!E11 -> 3000 | F11: =SUMPRODUCT((Movimento!$C$8:$C$407<>"")*(TEXT(Movimento!$C$8:$C$407,"yyyy-mm-dd")=TEXT($C11,"yyyy-mm-dd"))*Movimento!$F$8:$F$407) -> 0 | G11: =IF($E11=0,"",IFERROR($F11/$E11,0)) -> 0 | H11: =IF(AND($E11>0,$F11>=$E11),1,0) -> 0 | I11: =I10+$F11 -> 0 | J11: =J10+$E11 -> 15000 | K11: =I11-J11 -> -15000
C12: =Calendário!C12 -> 46271 | D12: =Calendário!D12 -> Não | E12: =Calendário!E12 -> 0 | F12: =SUMPRODUCT((Movimento!$C$8:$C$407<>"")*(TEXT(Movimento!$C$8:$C$407,"yyyy-mm-dd")=TEXT($C12,"yyyy-mm-dd"))*Movimento!$F$8:$F$407) -> 0 | G12: =IF($E12=0,"",IFERROR($F12/$E12,0)) | H12: =IF(AND($E12>0,$F12>=$E12),1,0) -> 0 | I12: =I11+$F12 -> 0 | J12: =J11+$E12 -> 15000 | K12: =I12-J12 -> -15000
C13: =Calendário!C13 -> 46272 | D13: =Calendário!D13 -> Sim | E13: =Calendário!E13 -> 3000 | F13: =SUMPRODUCT((Movimento!$C$8:$C$407<>"")*(TEXT(Movimento!$C$8:$C$407,"yyyy-mm-dd")=TEXT($C13,"yyyy-mm-dd"))*Movimento!$F$8:$F$407) -> 0 | G13: =IF($E13=0,"",IFERROR($F13/$E13,0)) -> 0 | H13: =IF(AND($E13>0,$F13>=$E13),1,0) -> 0 | I13: =I12+$F13 -> 0 | J13: =J12+$E13 -> 18000 | K13: =I13-J13 -> -18000
C14: =Calendário!C14 -> 46273 | D14: =Calendário!D14 -> Sim | E14: =Calendário!E14 -> 3000 | F14: =SUMPRODUCT((Movimento!$C$8:$C$407<>"")*(TEXT(Movimento!$C$8:$C$407,"yyyy-mm-dd")=TEXT($C14,"yyyy-mm-dd"))*Movimento!$F$8:$F$407) -> 0 | G14: =IF($E14=0,"",IFERROR($F14/$E14,0)) -> 0 | H14: =IF(AND($E14>0,$F14>=$E14),1,0) -> 0 | I14: =I13+$F14 -> 0 | J14: =J13+$E14 -> 21000 | K14: =I14-J14 -> -21000
C15: =Calendário!C15 -> 46274 | D15: =Calendário!D15 -> Sim | E15: =Calendário!E15 -> 3000 | F15: =SUMPRODUCT((Movimento!$C$8:$C$407<>"")*(TEXT(Movimento!$C$8:$C$407,"yyyy-mm-dd")=TEXT($C15,"yyyy-mm-dd"))*Movimento!$F$8:$F$407) -> 0 | G15: =IF($E15=0,"",IFERROR($F15/$E15,0)) -> 0 | H15: =IF(AND($E15>0,$F15>=$E15),1,0) -> 0 | I15: =I14+$F15 -> 0 | J15: =J14+$E15 -> 24000 | K15: =I15-J15 -> -24000
C16: =Calendário!C16 -> 46275 | D16: =Calendário!D16 -> Sim | E16: =Calendário!E16 -> 3000 | F16: =SUMPRODUCT((Movimento!$C$8:$C$407<>"")*(TEXT(Movimento!$C$8:$C$407,"yyyy-mm-dd")=TEXT($C16,"yyyy-mm-dd"))*Movimento!$F$8:$F$407) -> 0 | G16: =IF($E16=0,"",IFERROR($F16/$E16,0)) -> 0 | H16: =IF(AND($E16>0,$F16>=$E16),1,0) -> 0 | I16: =I15+$F16 -> 0 | J16: =J15+$E16 -> 27000 | K16: =I16-J16 -> -27000
C17: =Calendário!C17 -> 46276 | D17: =Calendário!D17 -> Sim | E17: =Calendário!E17 -> 3000 | F17: =SUMPRODUCT((Movimento!$C$8:$C$407<>"")*(TEXT(Movimento!$C$8:$C$407,"yyyy-mm-dd")=TEXT($C17,"yyyy-mm-dd"))*Movimento!$F$8:$F$407) -> 0 | G17: =IF($E17=0,"",IFERROR($F17/$E17,0)) -> 0 | H17: =IF(AND($E17>0,$F17>=$E17),1,0) -> 0 | I17: =I16+$F17 -> 0 | J17: =J16+$E17 -> 30000 | K17: =I17-J17 -> -30000
C18: =Calendário!C18 -> 46277 | D18: =Calendário!D18 -> Sim | E18: =Calendário!E18 -> 3000 | F18: =SUMPRODUCT((Movimento!$C$8:$C$407<>"")*(TEXT(Movimento!$C$8:$C$407,"yyyy-mm-dd")=TEXT($C18,"yyyy-mm-dd"))*Movimento!$F$8:$F$407) -> 0 | G18: =IF($E18=0,"",IFERROR($F18/$E18,0)) -> 0 | H18: =IF(AND($E18>0,$F18>=$E18),1,0) -> 0 | I18: =I17+$F18 -> 0 | J18: =J17+$E18 -> 33000 | K18: =I18-J18 -> -33000
C19: =Calendário!C19 -> 46278 | D19: =Calendário!D19 -> Não | E19: =Calendário!E19 -> 0 | F19: =SUMPRODUCT((Movimento!$C$8:$C$407<>"")*(TEXT(Movimento!$C$8:$C$407,"yyyy-mm-dd")=TEXT($C19,"yyyy-mm-dd"))*Movimento!$F$8:$F$407) -> 0 | G19: =IF($E19=0,"",IFERROR($F19/$E19,0)) | H19: =IF(AND($E19>0,$F19>=$E19),1,0) -> 0 | I19: =I18+$F19 -> 0 | J19: =J18+$E19 -> 33000 | K19: =I19-J19 -> -33000
... C36: =Calendário!C36 -> 46295 | D36: =Calendário!D36 -> Sim | E36: =Calendário!E36 -> 3000 | F36: =SUMPRODUCT((Movimento!$C$8:$C$407<>"")*(TEXT(Movimento!$C$8:$C$407,"yyyy-mm-dd")=TEXT($C36,"yyyy-mm-dd"))*Movimento!$F$8:$F$407) -> 0 | G36: =IF($E36=0,"",IFERROR($F36/$E36,0)) -> 0 | H36: =IF(AND($E36>0,$F36>=$E36),1,0) -> 0 | I36: =I35+$F36 -> 0 | J36: =J35+$E36 -> 78000 | K36: =I36-J36 -> -78000
C37: TOTAL | E37: =SUM(E7:E36) -> 78000 | F37: =SUM(F7:F36) -> 0 | G37: =IFERROR(F37/E37,0) -> 0 | H37: =SUM(H7:H36) -> 0 | I37: =I36 -> 0 | K37: =I37-E37 -> -78000

Sheet Apresentação
C1: SORRISO MAIOR
C2: SETEMBRO / 2026
C4: META | E4: VENDIDO | G4: TENDÊNCIA | I4: ATINGIMENTO
C5: =Calendário!$D$4 -> 78000 | E5: =Movimento!$D$4 -> 0 | G5: =Movimento!$J$4 -> 0 | I5: =IFERROR(Movimento!$D$4/Calendário!$D$4,0) -> 0
C7: DIAS QUE BATERAM A META
C8: ='Dia a Dia'!H37&" de "&Calendário!$E$4&" dias trabalhados" -> 0 de 26 dias trabalhados
C10: POR PROCEDIMENTO | G10: POR RECEBIMENTO
C11: Procedimento | D11: Valor | E11: % | G11: Forma | H11: Valor | I11: %
C12: Clínico | D12: =SUMIFS(Movimento!$F$8:$F$407,Movimento!$D$8:$D$407,$C12) -> 0 | E12: =IFERROR(D12/Movimento!$D$4,0) -> 0 | G12: Crédito | H12: =SUMIFS(Movimento!$F$8:$F$407,Movimento!$E$8:$E$407,$G12) -> 0 | I12: =IFERROR(H12/Movimento!$D$4,0) -> 0
C13: Ortodontia | D13: =SUMIFS(Movimento!$F$8:$F$407,Movimento!$D$8:$D$407,$C13) -> 0 | E13: =IFERROR(D13/Movimento!$D$4,0) -> 0 | G13: Débito | H13: =SUMIFS(Movimento!$F$8:$F$407,Movimento!$E$8:$E$407,$G13) -> 0 | I13: =IFERROR(H13/Movimento!$D$4,0) -> 0
C14: Prótese | D14: =SUMIFS(Movimento!$F$8:$F$407,Movimento!$D$8:$D$407,$C14) -> 0 | E14: =IFERROR(D14/Movimento!$D$4,0) -> 0 | G14: PIX | H14: =SUMIFS(Movimento!$F$8:$F$407,Movimento!$E$8:$E$407,$G14) -> 0 | I14: =IFERROR(H14/Movimento!$D$4,0) -> 0
C15: Implante | D15: =SUMIFS(Movimento!$F$8:$F$407,Movimento!$D$8:$D$407,$C15) -> 0 | E15: =IFERROR(D15/Movimento!$D$4,0) -> 0 | G15: Financeira | H15: =SUMIFS(Movimento!$F$8:$F$407,Movimento!$E$8:$E$407,$G15) -> 0 | I15: =IFERROR(H15/Movimento!$D$4,0) -> 0
C16: Estética | D16: =SUMIFS(Movimento!$F$8:$F$407,Movimento!$D$8:$D$407,$C16) -> 0 | E16: =IFERROR(D16/Movimento!$D$4,0) -> 0 | G16: Dinheiro | H16: =SUMIFS(Movimento!$F$8:$F$407,Movimento!$E$8:$E$407,$G16) -> 0 | I16: =IFERROR(H16/Movimento!$D$4,0) -> 0
C17: Avaliação | D17: =SUMIFS(Movimento!$F$8:$F$407,Movimento!$D$8:$D$407,$C17) -> 0 | E17: =IFERROR(D17/Movimento!$D$4,0) -> 0 | G17: Boleto | H17: =SUMIFS(Movimento!$F$8:$F$407,Movimento!$E$8:$E$407,$G17) -> 0 | I17: =IFERROR(H17/Movimento!$D$4,0) -> 0
G18: Convênio | H18: =SUMIFS(Movimento!$F$8:$F$407,Movimento!$E$8:$E$407,$G18) -> 0 | I18: =IFERROR(H18/Movimento!$D$4,0) -> 0
C20: RESULTADO DO MÊS
C21: Receita | D21: =Movimento!$D$4 -> 0
C22: Despesas | D22: =Despesas!$D$5 -> 0
C23: Resultado | D23: =D21-D22 -> 0
C24: Margem | D24: =IFERROR(D23/D21,0) -> 0
