Workbook

Sheet Dia a Dia
C1: SORRISO MAIOR · SETEMBRO 2026
C2: Lance o caixa do dia nas colunas azuis. Total, acumulado e atingimento se calculam sozinhos.
C4: Meta do mês | D4: 78000 | E4: Dias úteis | F4: 22 | G4: Meta por dia útil | I4: =IFERROR($D$4/$F$4,0) -> 3545.4545
C6: Data | D6: Meta do dia | E6: Crédito | F6: Débito | G6: PIX | H6: Financeira | I6: Dinheiro | J6: Boleto | K6: Total do dia | L6: Acumulado | M6: % da meta
C7: 46266 | D7: =IF(WEEKDAY(C7,2)>5,0,$I$4) -> 3545.4545 | K7: =SUM(E7:J7) -> 0 | L7: =K7 -> 0 | M7: =IFERROR(K7/D7,"") -> 0
C8: 46267 | D8: =IF(WEEKDAY(C8,2)>5,0,$I$4) -> 3545.4545 | K8: =SUM(E8:J8) -> 0 | L8: =L7+K8 -> 0 | M8: =IFERROR(K8/D8,"") -> 0
C9: 46268 | D9: =IF(WEEKDAY(C9,2)>5,0,$I$4) -> 3545.4545 | K9: =SUM(E9:J9) -> 0 | L9: =L8+K9 -> 0 | M9: =IFERROR(K9/D9,"") -> 0
C10: 46269 | D10: =IF(WEEKDAY(C10,2)>5,0,$I$4) -> 3545.4545 | K10: =SUM(E10:J10) -> 0 | L10: =L9+K10 -> 0 | M10: =IFERROR(K10/D10,"") -> 0
C11: 46270 | D11: =IF(WEEKDAY(C11,2)>5,0,$I$4) -> 0 | K11: =SUM(E11:J11) -> 0 | L11: =L10+K11 -> 0 | M11: =IFERROR(K11/D11,"")
C12: 46271 | D12: =IF(WEEKDAY(C12,2)>5,0,$I$4) -> 0 | K12: =SUM(E12:J12) -> 0 | L12: =L11+K12 -> 0 | M12: =IFERROR(K12/D12,"")
C13: 46272 | D13: =IF(WEEKDAY(C13,2)>5,0,$I$4) -> 3545.4545 | K13: =SUM(E13:J13) -> 0 | L13: =L12+K13 -> 0 | M13: =IFERROR(K13/D13,"") -> 0
C14: 46273 | D14: =IF(WEEKDAY(C14,2)>5,0,$I$4) -> 3545.4545 | K14: =SUM(E14:J14) -> 0 | L14: =L13+K14 -> 0 | M14: =IFERROR(K14/D14,"") -> 0
C15: 46274 | D15: =IF(WEEKDAY(C15,2)>5,0,$I$4) -> 3545.4545 | K15: =SUM(E15:J15) -> 0 | L15: =L14+K15 -> 0 | M15: =IFERROR(K15/D15,"") -> 0
C16: 46275 | D16: =IF(WEEKDAY(C16,2)>5,0,$I$4) -> 3545.4545 | K16: =SUM(E16:J16) -> 0 | L16: =L15+K16 -> 0 | M16: =IFERROR(K16/D16,"") -> 0
C17: 46276 | D17: =IF(WEEKDAY(C17,2)>5,0,$I$4) -> 3545.4545 | K17: =SUM(E17:J17) -> 0 | L17: =L16+K17 -> 0 | M17: =IFERROR(K17/D17,"") -> 0
C18: 46277 | D18: =IF(WEEKDAY(C18,2)>5,0,$I$4) -> 0 | K18: =SUM(E18:J18) -> 0 | L18: =L17+K18 -> 0 | M18: =IFERROR(K18/D18,"")
C19: 46278 | D19: =IF(WEEKDAY(C19,2)>5,0,$I$4) -> 0 | K19: =SUM(E19:J19) -> 0 | L19: =L18+K19 -> 0 | M19: =IFERROR(K19/D19,"")
... C36: 46295 | D36: =IF(WEEKDAY(C36,2)>5,0,$I$4) -> 3545.4545 | K36: =SUM(E36:J36) -> 0 | L36: =L35+K36 -> 0 | M36: =IFERROR(K36/D36,"") -> 0
C37: TOTAL DO MÊS | D37: =SUM(D7:D36) -> 78000 | E37: =SUM(E7:E36) -> 0 | F37: =SUM(F7:F36) -> 0 | G37: =SUM(G7:G36) -> 0 | H37: =SUM(H7:H36) -> 0 | I37: =SUM(I7:I36) -> 0 | J37: =SUM(J7:J36) -> 0 | K37: =SUM(K7:K36) -> 0 | L37: =L36 -> 0 | M37: =IFERROR(K37/$D$4,0) -> 0

Sheet Despesas
C1: DESPESAS · SETEMBRO 2026
C2: Cada saída de dinheiro, uma linha. É isto que vira o custo no DRE.
C5: Data | D5: Categoria | E5: Fornecedor / Descrição | F5: Valor | G5: Status
C156: TOTAL DE DESPESAS | F156: =SUM(F6:F155) -> 0

Sheet Listas
A1: 0. Custos Diretos
A2: 1. Administrativa
A3: 2.Financeira
A4: 3.Ocupação
A5: 4.Despesas com Marketing
A6: 5.Despesa com Utilidades
A7: 6.Despesa com Pessoal
A8: 7.Despesas Comerciais
A9: 9. Administração Pinheiro
A10: 10.Tributos
A11: Deduções da Receita Bruta
A12: Despesas Empreendedor

Sheet Fechamento
C1: FECHAMENTO · SETEMBRO 2026
C2: Nada se digita aqui. É esta linha que você leva para o DRE consolidado.
C4: RECEITA
C5: Meta do mês | D5: ='Dia a Dia'!$D$4 -> 78000
C6: Realizado | D6: ='Dia a Dia'!K37 -> 0
C7: Atingimento | D7: =IFERROR(D6/D5,0) -> 0
C9: POR FORMA DE PAGAMENTO
C10: Crédito | D10: ='Dia a Dia'!E37 -> 0 | E10: =IFERROR(D10/$D$6,0) -> 0
C11: Débito | D11: ='Dia a Dia'!F37 -> 0 | E11: =IFERROR(D11/$D$6,0) -> 0
C12: PIX | D12: ='Dia a Dia'!G37 -> 0 | E12: =IFERROR(D12/$D$6,0) -> 0
C13: Financeira | D13: ='Dia a Dia'!H37 -> 0 | E13: =IFERROR(D13/$D$6,0) -> 0
C14: Dinheiro | D14: ='Dia a Dia'!I37 -> 0 | E14: =IFERROR(D14/$D$6,0) -> 0
C15: Boleto | D15: ='Dia a Dia'!J37 -> 0 | E15: =IFERROR(D15/$D$6,0) -> 0
C17: DESPESAS
C18: Total de despesas | D18: =Despesas!F156 -> 0
C19: 0. Custos Diretos | D19: =SUMIFS(Despesas!$F:$F,Despesas!$D:$D,$C19) -> 0 | E19: =IFERROR(D19/$D$18,0) -> 0
C20: 1. Administrativa | D20: =SUMIFS(Despesas!$F:$F,Despesas!$D:$D,$C20) -> 0 | E20: =IFERROR(D20/$D$18,0) -> 0
C21: 2.Financeira | D21: =SUMIFS(Despesas!$F:$F,Despesas!$D:$D,$C21) -> 0 | E21: =IFERROR(D21/$D$18,0) -> 0
C22: 3.Ocupação | D22: =SUMIFS(Despesas!$F:$F,Despesas!$D:$D,$C22) -> 0 | E22: =IFERROR(D22/$D$18,0) -> 0
C23: 4.Despesas com Marketing | D23: =SUMIFS(Despesas!$F:$F,Despesas!$D:$D,$C23) -> 0 | E23: =IFERROR(D23/$D$18,0) -> 0
C24: 5.Despesa com Utilidades | D24: =SUMIFS(Despesas!$F:$F,Despesas!$D:$D,$C24) -> 0 | E24: =IFERROR(D24/$D$18,0) -> 0
C25: 6.Despesa com Pessoal | D25: =SUMIFS(Despesas!$F:$F,Despesas!$D:$D,$C25) -> 0 | E25: =IFERROR(D25/$D$18,0) -> 0
C26: 7.Despesas Comerciais | D26: =SUMIFS(Despesas!$F:$F,Despesas!$D:$D,$C26) -> 0 | E26: =IFERROR(D26/$D$18,0) -> 0
C27: 9. Administração Pinheiro | D27: =SUMIFS(Despesas!$F:$F,Despesas!$D:$D,$C27) -> 0 | E27: =IFERROR(D27/$D$18,0) -> 0
C28: 10.Tributos | D28: =SUMIFS(Despesas!$F:$F,Despesas!$D:$D,$C28) -> 0 | E28: =IFERROR(D28/$D$18,0) -> 0
C29: Deduções da Receita Bruta | D29: =SUMIFS(Despesas!$F:$F,Despesas!$D:$D,$C29) -> 0 | E29: =IFERROR(D29/$D$18,0) -> 0
C30: Despesas Empreendedor | D30: =SUMIFS(Despesas!$F:$F,Despesas!$D:$D,$C30) -> 0 | E30: =IFERROR(D30/$D$18,0) -> 0
C32: RESULTADO DO MÊS | D32: =D6-D18 -> 0
C33: Margem | D33: =IFERROR(D32/D6,0) -> 0
