Workbook

Sheet Categorias
A1: Categoria | B1: Tipo
A2: Particulares | B2: Receita
A3: 0. Custos Diretos | B3: Despesa
A4: 1. Administrativa | B4: Despesa
A5: 2.Financeira | B5: Despesa
A6: 3.Ocupação | B6: Despesa
A7: 4.Despesas com Marketing | B7: Despesa
A8: 5.Despesa com Utilidades | B8: Despesa
A9: 6.Despesa com Pessoal | B9: Despesa
A10: 7.Despesas Comerciais | B10: Despesa
A11: 9. Administração Pinheiro | B11: Despesa
A12: 10.Tributos | B12: Despesa
... A14: Despesas Empreendedor | B14: Despesa

Sheet Lançamentos
A1: LANÇAMENTOS — uma linha por movimento. Preencha só as colunas A a D.
A3: Data | B3: Categoria | C3: Fornecedor / Descrição | D3: Valor | E3: Tipo (automático) | F3: Competência (automático)
A4: 46113 | B4: Particulares | C4: VENDA CLINICO | D4: 65687.33 | E4: =IFERROR(INDEX(Categorias!$B:$B,MATCH(B4,Categorias!$A:$A,0)),"?") -> Receita | F4: =IF(A4="","",TEXT(A4,"YYYY-MM")) -> 2026-04
A5: 46113 | B5: Particulares | C5: VENDA ORTO | D5: 4288 | E5: =IFERROR(INDEX(Categorias!$B:$B,MATCH(B5,Categorias!$A:$A,0)),"?") -> Receita | F5: =IF(A5="","",TEXT(A5,"YYYY-MM")) -> 2026-04
A6: 46113 | B6: 0. Custos Diretos | C6: LAB DENT | D6: 3762.12 | E6: =IFERROR(INDEX(Categorias!$B:$B,MATCH(B6,Categorias!$A:$A,0)),"?") -> Despesa | F6: =IF(A6="","",TEXT(A6,"YYYY-MM")) -> 2026-04
A7: 46113 | B7: 6.Despesa com Pessoal | C7: RECISÃO EMILIA | D7: 1417.22 | E7: =IFERROR(INDEX(Categorias!$B:$B,MATCH(B7,Categorias!$A:$A,0)),"?") -> Despesa | F7: =IF(A7="","",TEXT(A7,"YYYY-MM")) -> 2026-04
A8: 46113 | B8: 0. Custos Diretos | C8: MATERIAL ODONTO | D8: 112.18 | E8: =IFERROR(INDEX(Categorias!$B:$B,MATCH(B8,Categorias!$A:$A,0)),"?") -> Despesa | F8: =IF(A8="","",TEXT(A8,"YYYY-MM")) -> 2026-04
A9: 46113 | B9: 6.Despesa com Pessoal | C9: SINDICATO | D9: 34 | E9: =IFERROR(INDEX(Categorias!$B:$B,MATCH(B9,Categorias!$A:$A,0)),"?") -> Despesa | F9: =IF(A9="","",TEXT(A9,"YYYY-MM")) -> 2026-04
A10: 46113 | B10: Despesas Empreendedor | C10: LABORATORIO SANTO AMARO | D10: 4531.44 | E10: =IFERROR(INDEX(Categorias!$B:$B,MATCH(B10,Categorias!$A:$A,0)),"?") -> Despesa | F10: =IF(A10="","",TEXT(A10,"YYYY-MM")) -> 2026-04
A11: 46113 | B11: 1. Administrativa | C11: MATERIAL DE USO CONSUMO | D11: 394.32 | E11: =IFERROR(INDEX(Categorias!$B:$B,MATCH(B11,Categorias!$A:$A,0)),"?") -> Despesa | F11: =IF(A11="","",TEXT(A11,"YYYY-MM")) -> 2026-04
A12: 46113 | B12: 0. Custos Diretos | C12: MATERIAL ODONTO | D12: 375 | E12: =IFERROR(INDEX(Categorias!$B:$B,MATCH(B12,Categorias!$A:$A,0)),"?") -> Despesa | F12: =IF(A12="","",TEXT(A12,"YYYY-MM")) -> 2026-04
A13: 46113 | B13: 6.Despesa com Pessoal | C13: ariadna asg | D13: 1846 | E13: =IFERROR(INDEX(Categorias!$B:$B,MATCH(B13,Categorias!$A:$A,0)),"?") -> Despesa | F13: =IF(A13="","",TEXT(A13,"YYYY-MM")) -> 2026-04
A14: 46113 | B14: 6.Despesa com Pessoal | C14: alimentação ariadna | D14: 256 | E14: =IFERROR(INDEX(Categorias!$B:$B,MATCH(B14,Categorias!$A:$A,0)),"?") -> Despesa | F14: =IF(A14="","",TEXT(A14,"YYYY-MM")) -> 2026-04
A15: 46113 | B15: 6.Despesa com Pessoal | C15: condução ariadna | D15: 236 | E15: =IFERROR(INDEX(Categorias!$B:$B,MATCH(B15,Categorias!$A:$A,0)),"?") -> Despesa | F15: =IF(A15="","",TEXT(A15,"YYYY-MM")) -> 2026-04
... A238: 46235 | B238: 0. Custos Diretos | C238: DENTAL CREMER | D238: 268.37 | E238: =IFERROR(INDEX(Categorias!$B:$B,MATCH(B238,Categorias!$A:$A,0)),"?") -> Despesa | F238: =IF(A238="","",TEXT(A238,"YYYY-MM")) -> 2026-08
E239: =IFERROR(INDEX(Categorias!$B:$B,MATCH(B239,Categorias!$A:$A,0)),"") | F239: =IF(A239="","",TEXT(A239,"YYYY-MM"))
E240: =IFERROR(INDEX(Categorias!$B:$B,MATCH(B240,Categorias!$A:$A,0)),"") | F240: =IF(A240="","",TEXT(A240,"YYYY-MM"))
E241: =IFERROR(INDEX(Categorias!$B:$B,MATCH(B241,Categorias!$A:$A,0)),"") | F241: =IF(A241="","",TEXT(A241,"YYYY-MM"))
E242: =IFERROR(INDEX(Categorias!$B:$B,MATCH(B242,Categorias!$A:$A,0)),"") | F242: =IF(A242="","",TEXT(A242,"YYYY-MM"))
E243: =IFERROR(INDEX(Categorias!$B:$B,MATCH(B243,Categorias!$A:$A,0)),"") | F243: =IF(A243="","",TEXT(A243,"YYYY-MM"))
E244: =IFERROR(INDEX(Categorias!$B:$B,MATCH(B244,Categorias!$A:$A,0)),"") | F244: =IF(A244="","",TEXT(A244,"YYYY-MM"))
E245: =IFERROR(INDEX(Categorias!$B:$B,MATCH(B245,Categorias!$A:$A,0)),"") | F245: =IF(A245="","",TEXT(A245,"YYYY-MM"))
E246: =IFERROR(INDEX(Categorias!$B:$B,MATCH(B246,Categorias!$A:$A,0)),"") | F246: =IF(A246="","",TEXT(A246,"YYYY-MM"))
E247: =IFERROR(INDEX(Categorias!$B:$B,MATCH(B247,Categorias!$A:$A,0)),"") | F247: =IF(A247="","",TEXT(A247,"YYYY-MM"))
E248: =IFERROR(INDEX(Categorias!$B:$B,MATCH(B248,Categorias!$A:$A,0)),"") | F248: =IF(A248="","",TEXT(A248,"YYYY-MM"))
E249: =IFERROR(INDEX(Categorias!$B:$B,MATCH(B249,Categorias!$A:$A,0)),"") | F249: =IF(A249="","",TEXT(A249,"YYYY-MM"))
E250: =IFERROR(INDEX(Categorias!$B:$B,MATCH(B250,Categorias!$A:$A,0)),"") | F250: =IF(A250="","",TEXT(A250,"YYYY-MM"))
... E298: =IFERROR(INDEX(Categorias!$B:$B,MATCH(B298,Categorias!$A:$A,0)),"") | F298: =IF(A298="","",TEXT(A298,"YYYY-MM"))

Sheet Painel
A1: PAINEL — Sorriso Maior
A2: Atualiza sozinho conforme a aba Lançamentos recebe linha nova.
A4: Competência | B4: Receita | C4: Custo | D4: Resultado | E4: Margem
A5: 2026-04 | B5: =SUMIFS(Lançamentos!$D:$D,Lançamentos!$F:$F,A5,Lançamentos!$E:$E,"Receita") -> 69975.33 | C5: =SUMIFS(Lançamentos!$D:$D,Lançamentos!$F:$F,A5,Lançamentos!$E:$E,"Despesa") -> 48768.39 | D5: =B5-C5 -> 21206.94 | E5: =IFERROR(D5/B5,0) -> 0.30306309
A6: 2026-05 | B6: =SUMIFS(Lançamentos!$D:$D,Lançamentos!$F:$F,A6,Lançamentos!$E:$E,"Receita") -> 67871.35 | C6: =SUMIFS(Lançamentos!$D:$D,Lançamentos!$F:$F,A6,Lançamentos!$E:$E,"Despesa") -> 40592.44 | D6: =B6-C6 -> 27278.91 | E6: =IFERROR(D6/B6,0) -> 0.40192084
A7: 2026-06 | B7: =SUMIFS(Lançamentos!$D:$D,Lançamentos!$F:$F,A7,Lançamentos!$E:$E,"Receita") -> 68367.51 | C7: =SUMIFS(Lançamentos!$D:$D,Lançamentos!$F:$F,A7,Lançamentos!$E:$E,"Despesa") -> 50560.97 | D7: =B7-C7 -> 17806.54 | E7: =IFERROR(D7/B7,0) -> 0.26045325
A8: 2026-07 | B8: =SUMIFS(Lançamentos!$D:$D,Lançamentos!$F:$F,A8,Lançamentos!$E:$E,"Receita") -> 116432.58 | C8: =SUMIFS(Lançamentos!$D:$D,Lançamentos!$F:$F,A8,Lançamentos!$E:$E,"Despesa") -> 60418.012 | D8: =B8-C8 -> 56014.568 | E8: =IFERROR(D8/B8,0) -> 0.48109016
A9: 2026-08 | B9: =SUMIFS(Lançamentos!$D:$D,Lançamentos!$F:$F,A9,Lançamentos!$E:$E,"Receita") -> 55327.85 | C9: =SUMIFS(Lançamentos!$D:$D,Lançamentos!$F:$F,A9,Lançamentos!$E:$E,"Despesa") -> 32937 | D9: =B9-C9 -> 22390.85 | E9: =IFERROR(D9/B9,0) -> 0.40469402
A10: TOTAL | B10: =SUM(B5:B9) -> 377974.62 | C10: =SUM(C5:C9) -> 233276.81 | D10: =SUM(D5:D9) -> 144697.81 | E10: =IFERROR(D10/B10,0) -> 0.38282414
A12: POR CATEGORIA (todo o período)
A13: Categoria | B13: Valor
A14: Particulares | B14: =SUMIFS(Lançamentos!$D:$D,Lançamentos!$B:$B,A14) -> 377974.62
A15: 0. Custos Diretos | B15: =SUMIFS(Lançamentos!$D:$D,Lançamentos!$B:$B,A15) -> 98312.992
A16: 1. Administrativa | B16: =SUMIFS(Lançamentos!$D:$D,Lançamentos!$B:$B,A16) -> 6704.02
A17: 2.Financeira | B17: =SUMIFS(Lançamentos!$D:$D,Lançamentos!$B:$B,A17) -> 2095.84
A18: 3.Ocupação | B18: =SUMIFS(Lançamentos!$D:$D,Lançamentos!$B:$B,A18) -> 27067.83
A19: 4.Despesas com Marketing | B19: =SUMIFS(Lançamentos!$D:$D,Lançamentos!$B:$B,A19) -> 5622.17
A20: 5.Despesa com Utilidades | B20: =SUMIFS(Lançamentos!$D:$D,Lançamentos!$B:$B,A20) -> 3269.94
A21: 6.Despesa com Pessoal | B21: =SUMIFS(Lançamentos!$D:$D,Lançamentos!$B:$B,A21) -> 42434.34
A22: 7.Despesas Comerciais | B22: =SUMIFS(Lançamentos!$D:$D,Lançamentos!$B:$B,A22) -> 1500
A23: 9. Administração Pinheiro | B23: =SUMIFS(Lançamentos!$D:$D,Lançamentos!$B:$B,A23) -> 27000
A24: 10.Tributos | B24: =SUMIFS(Lançamentos!$D:$D,Lançamentos!$B:$B,A24) -> 6262.48
A25: Deduções da Receita Bruta | B25: =SUMIFS(Lançamentos!$D:$D,Lançamentos!$B:$B,A25) -> 6960.76
A26: Despesas Empreendedor | B26: =SUMIFS(Lançamentos!$D:$D,Lançamentos!$B:$B,A26) -> 6046.44
